{"ticker": "HUBS", "timestamp": "2026-06-02T17:15:25.847217", "revenue_yoy_pct": 23.4, "eps_trend": "mixed", "gross_margin_pct": 83.7, "net_margin_pct": 3.0, "debt_to_equity": 0.12, "cash_usd_m": 1691.1, "net_cash_positive": true, "fcf_usd_m": 656.2, "fcf_to_ni_ratio": 6.54, "ps_ratio": 3.7, "pe_ratio": 124.5, "roe_pct": 5.0, "fundamental_score": 32, "fundamental_grade": "\u5f31", "fundamental_positives": ["\u8425\u6536\u540c\u6bd4 +23.4%", "\u51c0\u73b0\u91d1\uff08\u65e0\u503a\u52a1\u538b\u529b\uff09", "\u81ea\u7531\u73b0\u91d1\u6d41\u8d28\u91cf\u9ad8 FCF/NI=6.54"], "fundamental_warnings": ["EPS\u589e\u901f\u504f\u4f4e 0%", "\u51c0\u5229\u7387\u4ec5 3.0%"]}